[
    {
        "type":"generalMercenary",
        "desc":"普通雇佣兵",
        "sellDesc":"移速中,血量低,攻击低"
    },
    {
        "type":"celerityMercenary",
        "desc":"快速雇佣兵",
        "sellDesc":"移速快,血量中,攻击中"
    },
    {
        "type":"guardMercenary",
        "desc":"护卫雇佣兵",
        "sellDesc":"移速中,血量中,攻击中"
    },
    {
        "type":"bloodThickMercenary",
        "desc":"盾牌雇佣兵",
        "sellDesc":"移速慢,血量高,攻击高"
    },
    {
        "type":"sniperMercenary",
        "desc":"狙击手雇佣兵",
        "sellDesc":"移速中,血量低,攻击高"
    },
    {
        "type":"class16GeneralMercenary",
        "desc":"16课普通雇佣兵",
        "sellDesc":"移速中,血量低,攻击低"
    },
    {
        "type":"class16CelerityMercenary",
        "desc":"16课快速雇佣兵",
        "sellDesc":"移速快,血量中,攻击中"
    },
    {
        "type":"class16GuardMercenary",
        "desc":"16课护卫雇佣兵",
        "sellDesc":"移速中,血量中,攻击中"
    },
    {
        "type":"class16BloodThickMercenary",
        "desc":"16课盾牌雇佣兵",
        "sellDesc":"移速慢,血量高,攻击高"
    },
    {
        "type":"class16SniperMercenary",
        "desc":"16课狙击手雇佣兵",
        "sellDesc":"移速中,血量低,攻击高"
    }
]